atomicity-0.0.3.dist-info/METADATA
atomicity-0.0.3.dist-info/WHEEL
atomicity-0.0.3.dist-info/license_files/LICENSE
atomicity/__init__.py
atomicity/atomicity.cp310-win_amd64.pyd
atomicity-0.0.3.dist-info/RECORD
