Metadata-Version: 2.1
Name: atomicity
Version: 0.0.3
Classifier: Programming Language :: Python :: 3
Classifier: Programming Language :: Rust
Classifier: Programming Language :: Python :: Implementation :: CPython
Classifier: Programming Language :: Python :: Implementation :: PyPy
Classifier: Operating System :: POSIX
Classifier: Operating System :: MacOS :: MacOS X
Classifier: Operating System :: Microsoft :: Windows
License-File: LICENSE
Summary: Atomicity is a simple library to provide atomic operation to python's synchronization primitives for multi-threading
Author: BrØk3n Professional Services, inc.
Author-email: "BrØk3n Professional Services, inc." <support@br0k3n.ca>
Requires-Python: >=3.8, <3.11
